tochka_cyclops_api/__init__.py
tochka_cyclops_api/api.py
tochka_cyclops_api/constants.py
tochka_cyclops_api/errors.py
tochka_cyclops_api/utils.py
tochka_cyclops_api-0.3.1.dist-info/METADATA
tochka_cyclops_api-0.3.1.dist-info/WHEEL
tochka_cyclops_api-0.3.1.dist-info/RECORD
