Metadata-Version: 2.1
Name: tochka-cyclops-api
Version: 0.3.1
Summary: Tochka API v2 aka Cyclops API
Home-page: https://github.com/s3rgeym/tochka-cyclops-api
Author: Sergey M
Requires-Python: >=3.11,<4.0
Classifier: Programming Language :: Python :: 3
Classifier: Programming Language :: Python :: 3.11
Classifier: Programming Language :: Python :: 3.12
Requires-Dist: pyopenssl (>=23.2.0,<24.0.0)
Requires-Dist: requests[socks] (>=2.31.0,<3.0.0)
Project-URL: Repository, https://github.com/s3rgeym/tochka-cyclops-api
